[{"credits":1500,"players":{"portieri":[null,null,null],"difensori":[null,null,null,null,null,null,null,null],"centrocampisti":[null,null,null,null,null,null,null,null],"attaccanti":[null,null,null,null,null,null]},"id":"squad-1"},{"credits":1500,"players":{"portieri":[null,null,null],"difensori":[null,null,null,null,null,null,null,null],"centrocampisti":[null,null,null,null,null,null,null,null],"attaccanti":[null,null,null,null,null,null]},"id":"squad-8"},{"credits":1500,"players":{"portieri":[null,null,null],"difensori":[null,null,null,null,null,null,null,null],"centrocampisti":[null,null,null,null,null,null,null,null],"attaccanti":[null,null,null,null,null,null]},"id":"squad-6"},{"credits":1500,"players":{"portieri":[null,null,null],"difensori":[null,null,null,null,null,null,null,null],"centrocampisti":[null,null,null,null,null,null,null,null],"attaccanti":[null,null,null,null,null,null]},"id":"squad-10"},{"credits":1500,"players":{"portieri":[null,null,null],"difensori":[null,null,null,null,null,null,null,null],"centrocampisti":[null,null,null,null,null,null,null,null],"attaccanti":[null,null,null,null,null,null]},"id":"squad-5"},{"credits":1500,"players":{"portieri":[null,null,null],"difensori":[null,null,null,null,null,null,null,null],"centrocampisti":[null,null,null,null,null,null,null,null],"attaccanti":[null,null,null,null,null,null]},"id":"squad-4"},{"credits":1500,"players":{"portieri":[null,null,null],"difensori":[null,null,null,null,null,null,null,null],"centrocampisti":[null,null,null,null,null,null,null,null],"attaccanti":[null,null,null,null,null,null]},"id":"squad-9"},{"credits":1500,"players":{"portieri":[null,null,null],"difensori":[null,null,null,null,null,null,null,null],"centrocampisti":[null,null,null,null,null,null,null,null],"attaccanti":[null,null,null,null,null,null]},"id":"squad-7"},{"credits":1500,"players":{"portieri":[null,null,null],"difensori":[null,null,null,null,null,null,null,null],"centrocampisti":[null,null,null,null,null,null,null,null],"attaccanti":[null,null,null,null,null,null]},"id":"squad-3"},{"credits":1500,"players":{"portieri":[null,null,null],"difensori":[null,null,null,null,null,null,null,null],"centrocampisti":[null,null,null,null,null,null,null,null],"attaccanti":[null,null,null,null,null,null]},"id":"squad-2"}]